Workbook

Sheet Cost Plan
A1: Urban Highway Improvement Scheme — Elemental Cost Plan
A2: ="Meridian Cost Consultants | Report Date: "&TEXT(TODAY(),"DD MMMM YYYY") -> Meridian Cost Consultants | Report Date: 16 May 2026
A4: Element Ref | B4: Element Description | C4: Budget (£) | D4: Authorised Changes (£) | E4: Revised Budget (£) | F4: Committed (£) | G4: Actual to Date (£) | H4: Forecast Final Cost (£) | I4: Variance (£) | J4: % Complete
A5: 1.0 | B5: Demolition & Site Clearance | C5: =SUM(C6:C8) -> 1280000 | D5: =SUM(D6:D8) -> 180000 | E5: =SUM(E6:E8) -> 1460000 | F5: =SUM(F6:F8) -> 1440000 | G5: =SUM(G6:G8) -> 1340000 | H5: =SUM(H6:H8) -> 1580000 | I5: =E5-H5 -> -120000 | J5: =SUMPRODUCT(E6:E8, J6:J8)/SUM(E6:E8) -> 0.94863014
A6: 1.1 | B6: Demolition of Existing Structures | C6: 640000 | E6: =SUM(C6:D6) -> 640000 | F6: 640000 | G6: 640000 | H6: 640000 | I6: =E6-H6 -> 0 | J6: 1
A7: 1.2 | B7: Site Clearance & Stripping | C7: 320000 | E7: =SUM(C7:D7) -> 320000 | F7: 320000 | G7: 320000 | H7: 320000 | I7: =E7-H7 -> 0 | J7: 1
A8: 1.3 | B8: Contamination Remediation | C8: 320000 | D8: 180000 | E8: =SUM(C8:D8) -> 500000 | F8: 480000 | G8: 380000 | H8: 620000 | I8: =E8-H8 -> -120000 | J8: 0.85
A9: 2.0 | B9: Earthworks | C9: =SUM(C10:C12) -> 6400000 | D9: =SUM(D10:D12) -> 95000 | E9: =SUM(E10:E12) -> 6495000 | F9: =SUM(F10:F12) -> 5695000 | G9: =SUM(G10:G12) -> 4560000 | H9: =SUM(H10:H12) -> 7100000 | I9: =E9-H9 -> -605000 | J9: =SUMPRODUCT(E10:E12,J10:J12)/SUM(E10:E12) -> 0.6687067
A10: 2.1 | B10: Bulk Excavation & Filling | C10: 3200000 | D10: 95000 | E10: =SUM(C10:D10) -> 3295000 | F10: 3295000 | G10: 2640000 | H10: 3580000 | I10: =E10-H10 -> -285000 | J10: 0.75
A11: 2.2 | B11: Embankments & Cuttings | C11: 2240000 | E11: =SUM(C11:D11) -> 2240000 | F11: 1680000 | G11: 1344000 | H11: 2420000 | I11: =E11-H11 -> -180000 | J11: 0.6
A12: 2.3 | B12: Temporary Works & Support | C12: 960000 | E12: =SUM(C12:D12) -> 960000 | F12: 720000 | G12: 576000 | H12: 1100000 | I12: =E12-H12 -> -140000 | J12: 0.55
A13: 3.0 | B13: Pavements | C13: =SUM(C14:C15) -> 5760000 | D13: =SUM(D14:D15) -> 0 | E13: =SUM(E14:E15) -> 5760000 | F13: =SUM(F14:F15) -> 3328000 | G13: =SUM(G14:G15) -> 1664000 | H13: =SUM(H14:H15) -> 5760000 | I13: =E13-H13 -> 0 | J13: =SUMPRODUCT(E14:E15,J14:J15)/SUM(E14:E15) -> 0.28888889
A14: 3.1 | B14: Carriageway Construction | C14: 4480000 | E14: =SUM(C14:D14) -> 4480000 | F14: 2688000 | G14: 1344000 | H14: 4480000 | I14: =E14-H14 -> 0 | J14: 0.3
A15: 3.2 | B15: Footways & Cycleways | C15: 1280000 | E15: =SUM(C15:D15) -> 1280000 | F15: 640000 | G15: 320000 | H15: 1280000 | I15: =E15-H15 -> 0 | J15: 0.25
A16: 4.0 | B16: Structures | C16: =SUM(C17:C19) -> 7040000 | D16: =SUM(D17:D19) -> 220000 | E16: =SUM(E17:E19) -> 7260000 | F16: =SUM(F17:F19) -> 5664000 | G16: =SUM(G17:G19) -> 3648000 | H16: =SUM(H17:H19) -> 7650000 | I16: =E16-H16 -> -390000 | J16: =SUMPRODUCT(E17:E19,J17:J19)/SUM(E17:E19) -> 0.47947658
A17: 4.1 | B17: Bridges & Culverts | C17: 4800000 | D17: 220000 | E17: =SUM(C17:D17) -> 5020000 | F17: 4320000 | G17: 2880000 | H17: 5200000 | I17: =E17-H17 -> -180000 | J17: 0.55
A18: 4.2 | B18: Retaining Walls | C18: 1600000 | E18: =SUM(C18:D18) -> 1600000 | F18: 960000 | G18: 576000 | H18: 1750000 | I18: =E18-H18 -> -150000 | J18: 0.35
A19: 4.3 | B19: Drainage Structures | C19: 640000 | E19: =SUM(C19:D19) -> 640000 | F19: 384000 | G19: 192000 | H19: 700000 | I19: =E19-H19 -> -60000 | J19: 0.25
A20: 5.0 | B20: Highway Services & Lighting | C20: =SUM(C21:C22) -> 2560000 | D20: =SUM(D21:D22) -> 0 | E20: =SUM(E21:E22) -> 2560000 | F20: =SUM(F21:F22) -> 928000 | G20: =SUM(G21:G22) -> 464000 | H20: =SUM(H21:H22) -> 2560000 | I20: =E20-H20 -> 0 | J20: =SUMPRODUCT(E21:E22,J21:J22)/SUM(E21:E22) -> 0.18125
A21: 5.1 | B21: Street Lighting | C21: 1600000 | E21: =SUM(C21:D21) -> 1600000 | F21: 640000 | G21: 320000 | H21: 1600000 | I21: =E21-H21 -> 0 | J21: 0.2
A22: 5.2 | B22: Traffic Signals & ITS | C22: 960000 | E22: =SUM(C22:D22) -> 960000 | F22: 288000 | G22: 144000 | H22: 960000 | I22: =E22-H22 -> 0 | J22: 0.15
A23: 6.0 | B23: Landscaping & Ecology | C23: 960000 | E23: =SUM(C23:D23) -> 960000 | F23: 192000 | G23: 0 | H23: 960000 | I23: =E23-H23 -> 0 | J23: 0
A24: 7.0 | B24: Preliminaries | C24: 5760000 | D24: 145000 | E24: =SUM(C24:D24) -> 5905000 | F24: 5905000 | G24: 2962500 | H24: 6200000 | I24: =E24-H24 -> -295000 | J24: 0.45
A25: 8.0 | B25: Contingency | C25: 2240000 | E25: =SUM(C25:D25) -> 2240000 | F25: 0 | G25: 0 | H25: 1800000 | I25: =E25-H25 -> 440000 | J25: 0
B26: Total Project Cost | C26: =SUM(C5,C9,C13,C16,C20,C23,C24,C25) -> 32000000 | D26: =SUM(D5,D9,D13,D16,D20,D23,D24,D25) -> 640000 | E26: =SUM(E5,E9,E13,E16,E20,E23,E24,E25) -> 32640000 | F26: =SUM(F5,F9,F13,F16,F20,F23,F24,F25) -> 23152000 | G26: =SUM(G5,G9,G13,G16,G20,G23,G24,G25) -> 14638500 | H26: =SUM(H5,H9,H13,H16,H20,H23,H24,H25) -> 33610000 | I26: =E26-H26 -> -970000 | J26: =SUMPRODUCT(E5:E25,J5:J25)/SUM(E5:E25) -> 0.45094348

Sheet CVR
A1: Urban Highway Improvement Scheme — Cost Value Reconciliation
A2: Meridian Cost Consultants | Reporting Period: September 2024
A4: Month | B4: Cumulative Value (£) | C4: Cumulative Cost (£) | D4: Gross Margin (£) | E4: Margin % | F4: CPI | G4: EAC
A5: 45170 | B5: 480000 | C5: 510000 | D5: =B5-C5 -> -30000 | E5: =D5/B5 -> -0.0625 | F5: =B5/C5 -> 0.94117647 | G5: ='Cost Plan'!$E$26/F5 -> 34680000
A6: 45200 | B6: 980000 | C6: 1050000 | D6: =B6-C6 -> -70000 | E6: =D6/B6 -> -0.071428571 | F6: =B6/C6 -> 0.93333333 | G6: ='Cost Plan'!$E$26/F6 -> 34971429
A7: 45231 | B7: 1650000 | C7: 1780000 | D7: =B7-C7 -> -130000 | E7: =D7/B7 -> -0.078787879 | F7: =B7/C7 -> 0.92696629 | G7: ='Cost Plan'!$E$26/F7 -> 35211636
A8: 45261 | B8: 2100000 | C8: 2280000 | D8: =B8-C8 -> -180000 | E8: =D8/B8 -> -0.085714286 | F8: =B8/C8 -> 0.92105263 | G8: ='Cost Plan'!$E$26/F8 -> 35437714
A9: 45292 | B9: 2820000 | C9: 3050000 | D9: =B9-C9 -> -230000 | E9: =D9/B9 -> -0.081560284 | F9: =B9/C9 -> 0.92459016 | G9: ='Cost Plan'!$E$26/F9 -> 35302128
A10: 45323 | B10: 3680000 | C10: 3980000 | D10: =B10-C10 -> -300000 | E10: =D10/B10 -> -0.081521739 | F10: =B10/C10 -> 0.92462312 | G10: ='Cost Plan'!$E$26/F10 -> 35300870
A11: 45352 | B11: 4950000 | C11: 5280000 | D11: =B11-C11 -> -330000 | E11: =D11/B11 -> -0.066666667 | F11: =B11/C11 -> 0.9375 | G11: ='Cost Plan'!$E$26/F11 -> 34816000
A12: 45383 | B12: 6240000 | C12: 6620000 | D12: =B12-C12 -> -380000 | E12: =D12/B12 -> -0.060897436 | F12: =B12/C12 -> 0.94259819 | G12: ='Cost Plan'!$E$26/F12 -> 34627692
A13: 45413 | B13: 7680000 | C13: 8100000 | D13: =B13-C13 -> -420000 | E13: =D13/B13 -> -0.0546875 | F13: =B13/C13 -> 0.94814815 | G13: ='Cost Plan'!$E$26/F13 -> 34425000
A14: 45444 | B14: 9120000 | C14: 9650000 | D14: =B14-C14 -> -530000 | E14: =D14/B14 -> -0.058114035 | F14: =B14/C14 -> 0.94507772 | G14: ='Cost Plan'!$E$26/F14 -> 34536842
A15: 45474 | B15: 10560000 | C15: 11150000 | D15: =B15-C15 -> -590000 | E15: =D15/B15 -> -0.055871212 | F15: =B15/C15 -> 0.9470852 | G15: ='Cost Plan'!$E$26/F15 -> 34463636
A16: 45505 | B16: 11800000 | C16: 12450000 | D16: =B16-C16 -> -650000 | E16: =D16/B16 -> -0.055084746 | F16: =B16/C16 -> 0.94779116 | G16: ='Cost Plan'!$E$26/F16 -> 34437966
... A23: 45717 | B23: 16640000 | C23: 17610000 | D23: =B23-C23 -> -970000 | E23: =D23/B23 -> -0.058293269 | F23: =B23/C23 -> 0.94491766 | G23: ='Cost Plan'!$E$26/F23 -> 34542692
B1048576: =SUM(B1:B1048575) -> 167570000 | C1048576: =SUM(C1:C1048575) -> 177060000

Sheet Project Info
A1: Project Name | B1: Urban Highway Improvement Scheme
A2: Client | B2: Transport for Greater Manchester
A3: Contract Type | B3: NEC4 Engineering and Construction Contract
A4: Project Value | B4: 32000000
A5: Start Date | B5: 45170
A6: Completion Date | B6: 46081
A7: Project Manager | B7: Meridian Cost Consultants
A8: Status | B8: In Progress
A9: % Complete | B9: ='Cost Plan'!J26 -> 0.45094348
A10: Sector | B10: Infrastructure
